archwiki/.swp
archwiki/__init__.py
archwiki/archwiki.py
archwiki-0.3.0.dist-info/entry_points.txt
archwiki-0.3.0.dist-info/WHEEL
archwiki-0.3.0.dist-info/METADATA
archwiki-0.3.0.dist-info/RECORD
