Metadata-Version: 2.1
Name: archwiki
Version: 0.3.0
Summary: Explore e salve tópicos da biblioteca do ArchLinux
Author: renantamashiro
Requires-Python: >=3.8,<4.0
Classifier: Programming Language :: Python :: 3
Classifier: Programming Language :: Python :: 3.8
Requires-Dist: html2text (>=2020.1.16,<2021.0.0)
Requires-Dist: requests (>=2.24.0,<3.0.0)
